[
  {
    "id": 1,
    "category": "cosmetics",
    "text": "Cosmetics & Toiletries",
    "subcategories": [ "baby-care", "body-wash", "deodorants", "Fragrances", "grooming", "hair-care", "hair-colorant", "hair-styling", "hand-wash", "oral-care", "personal-hygiene", "shaving-products", "skin-care", "sun-care" ],
    "products": [
      {
        "category": "cosmetics",
        "subcategories": [ "grooming" ],
        "type": "distributed",
        "countries": [ "Bulgaria", "Czech", "Greece", "Hungary", "North-Macedonia", "Romania", "Slovakia" ],
        "partner": "sodalis-group",
        "logo": "/media/koja55ll/strep-logo.png?width=0\u0026height=150\u0026mode=crop\u0026quality=60",
        "title": "Personal Care",
        "text": "Grooming",
        "url": "/our-brands/personal-care/"
      },
      {
        "category": "cosmetics",
        "subcategories": [ "oral-care" ],
        "type": "distributed",
        "countries": [ "Bulgaria", "Czech", "Greece", "Poland", "Romania", "Slovakia" ],
        "partner": "church-dwight",
        "logo": "/media/slnl4y13/pearl-drops-logo.png?width=0\u0026height=150\u0026mode=crop\u0026quality=60",
        "title": "Personal Care",
        "text": "Oral Care",
        "url": "/our-brands/personal-care/"
      },
      {
        "category": "cosmetics",
        "subcategories": [ "body-wash" ],
        "type": "distributed",
        "countries": [ "Poland" ],
        "partner": "evyap",
        "logo": "/media/xioc5xdy/arko-logo.png?width=0\u0026height=150\u0026mode=crop\u0026quality=60",
        "title": "Personal Care",
        "text": "Body Wash",
        "url": "/our-brands/personal-care/"
      },
      {
        "category": "cosmetics",
        "subcategories": [ "personal-hygiene" ],
        "type": "distributed",
        "countries": [ "Bulgaria", "Greece" ],
        "partner": "church-dwight",
        "logo": "/media/jedozjnd/femfresh-final-black-logo.png?width=0\u0026height=150\u0026mode=crop\u0026quality=60",
        "title": "Personal Care",
        "text": "Personal Hygiene",
        "url": "/our-brands/personal-care/"
      },
      {
        "category": "cosmetics",
        "subcategories": [ "hair-styling" ],
        "type": "distributed",
        "countries": [ "Greece" ],
        "partner": "helen-of-troy",
        "logo": "/media/sa4j20cf/logo-filanet.png?width=0\u0026height=150\u0026mode=crop\u0026quality=60",
        "title": "Personal Care",
        "text": "Hair Styling",
        "url": "/our-brands/personal-care/"
      },
      {
        "category": "cosmetics",
        "subcategories": [ "hair-colorant" ],
        "type": "distributed",
        "countries": [ "Greece" ],
        "partner": "coty",
        "logo": "/media/21onitax/koleston-prof-logo.png?width=0\u0026height=150\u0026mode=crop\u0026quality=60",
        "title": "Personal Care",
        "text": "Hair Colorant",
        "url": "/our-brands/personal-care/"
      },
      {
        "category": "cosmetics",
        "subcategories": [ "skin-care", "sun-care" ],
        "type": "own",
        "countries": [ "Czech", "Slovakia" ],
        "partner": "",
        "logo": "/media/4cwba1i2/astrid-logo.png?width=0\u0026height=150\u0026mode=crop\u0026quality=60",
        "title": "Personal Care",
        "text": "Skin Care, Sun Care",
        "url": "/our-brands/personal-care/"
      },
      {
        "category": "cosmetics",
        "subcategories": [ "skin-care", "body-wash" ],
        "type": "own",
        "countries": [ "Bosnia", "Bulgaria", "Czech", "Greece", "North-Macedonia", "Poland", "Portugal", "Serbia", "Slovakia" ],
        "partner": "",
        "logo": "/media/0flp3dip/bioten-logo.png?width=0\u0026height=150\u0026mode=crop\u0026quality=60",
        "title": "Personal Care",
        "text": "Skin Care, Body Wash",
        "url": "/our-brands/personal-care/"
      },
      {
        "category": "cosmetics",
        "subcategories": [ "Fragrances", "deodorants", "body-wash", "grooming" ],
        "type": "own",
        "countries": [ "Bosnia", "Bulgaria", "Czech", "Greece", "Hungary", "North-Macedonia", "Poland", "Portugal", "Romania", "Serbia", "Slovakia", "Ukraine" ],
        "partner": "",
        "logo": "/media/puud00vc/new_logo_str8.png?width=0\u0026height=150\u0026mode=crop\u0026quality=60",
        "title": "Personal Care",
        "text": "Fragrances, Deodorants, Body Wash, Grooming",
        "url": "/our-brands/personal-care/"
      },
      {
        "category": "cosmetics",
        "subcategories": [ "Fragrances", "deodorants", "body-wash" ],
        "type": "own",
        "countries": [ "Bosnia", "Bulgaria", "Czech", "Greece", "Hungary", "North-Macedonia", "Portugal", "Romania", "Serbia", "Slovakia" ],
        "partner": "",
        "logo": "/media/5aye4a1k/bu-black-logo.png?width=0\u0026height=150\u0026mode=crop\u0026quality=60",
        "title": "Personal Care",
        "text": "Fragrances, Deodorants, Body Wash",
        "url": "/our-brands/personal-care/"
      },
      {
        "category": "cosmetics",
        "subcategories": [ "Fragrances", "deodorants" ],
        "type": "own",
        "countries": [ "Bulgaria", "Czech", "Greece", "Hungary", "North-Macedonia", "Poland", "Romania", "Serbia", "Slovakia" ],
        "partner": "",
        "logo": "/media/nazdtc4u/c-thru-logo.png?width=0\u0026height=150\u0026mode=crop\u0026quality=60",
        "title": "Personal Care",
        "text": "Fragrances, Deodorants",
        "url": "/our-brands/personal-care/"
      },
      {
        "category": "cosmetics",
        "subcategories": [ "Fragrances" ],
        "type": "own",
        "countries": [ "Bosnia", "Bulgaria", "Czech", "Greece", "Hungary", "North-Macedonia", "Poland", "Portugal", "Romania", "Serbia", "Slovakia" ],
        "partner": "",
        "logo": "/media/haqdzngs/elode_logo_new.png?width=0\u0026height=150\u0026mode=crop\u0026quality=60",
        "title": "Personal Care",
        "text": "Fragrances",
        "url": "/our-brands/personal-care/"
      },
      {
        "category": "cosmetics",
        "subcategories": [ "Fragrances" ],
        "type": "distributed",
        "countries": [ "Greece" ],
        "partner": "unilever",
        "logo": "/media/0omft1w4/μυρτω-logo.png?width=0\u0026height=150\u0026mode=crop\u0026quality=60",
        "title": "Personal Care",
        "text": "Fragrances",
        "url": "/our-brands/personal-care/"
      },
      {
        "category": "cosmetics",
        "subcategories": [ "sun-care" ],
        "type": "own",
        "countries": [ "Czech", "Slovakia" ],
        "partner": "",
        "logo": "/media/41ulfsg3/sahara-logo.png?width=0\u0026height=150\u0026mode=crop\u0026quality=60",
        "title": "Personal Care",
        "text": "Sun Care",
        "url": "/our-brands/personal-care/"
      },
      {
        "category": "cosmetics",
        "subcategories": [ "sun-care" ],
        "type": "own",
        "countries": [ "Greece", "Poland" ],
        "partner": "",
        "logo": "/media/0ablxnrp/kolastyna-logo.png?width=0\u0026height=150\u0026mode=crop\u0026quality=60",
        "title": "Personal Care",
        "text": "Sun Care",
        "url": "/our-brands/personal-care/"
      },
      {
        "category": "cosmetics",
        "subcategories": [ "grooming" ],
        "type": "own",
        "countries": [ "Greece" ],
        "partner": "",
        "logo": "/media/nq3fcv10/logo-prosar.png?width=0\u0026height=150\u0026mode=crop\u0026quality=60",
        "title": "Personal Care",
        "text": "Grooming",
        "url": "/our-brands/personal-care/"
      },
      {
        "category": "cosmetics",
        "subcategories": [ "sun-care" ],
        "type": "own",
        "countries": [ "Bulgaria", "Czech", "Greece", "North-Macedonia", "Serbia" ],
        "partner": "",
        "logo": "/media/c0kfktlq/carroten.png?width=0\u0026height=150\u0026mode=crop\u0026quality=60",
        "title": "Personal Care",
        "text": "Sun Care",
        "url": "/our-brands/personal-care/"
      },
      {
        "category": "cosmetics",
        "subcategories": [ "hair-care" ],
        "type": "own",
        "countries": [ "Bulgaria", "Greece" ],
        "partner": "",
        "logo": "/media/t4slivpc/orzene-logo.png?width=0\u0026height=150\u0026mode=crop\u0026quality=60",
        "title": "Personal Care",
        "text": "Hair Care",
        "url": "/our-brands/personal-care/"
      },
      {
        "category": "cosmetics",
        "subcategories": [ "body-wash", "hand-wash" ],
        "type": "own",
        "countries": [ "Poland" ],
        "partner": "",
        "logo": "/media/5f3nqusj/final-luksja-logo.png?width=0\u0026height=150\u0026mode=crop\u0026quality=60",
        "title": "Personal Care",
        "text": "Body Wash, Hand Wash",
        "url": "/our-brands/personal-care/"
      },
      {
        "category": "cosmetics",
        "subcategories": [ "deodorants", "body-wash", "hand-wash", "grooming" ],
        "type": "own",
        "countries": [ "Greece" ],
        "partner": "",
        "logo": "/media/nbugvmwa/νοχζεμα-logo.png?width=0\u0026height=150\u0026mode=crop\u0026quality=60",
        "title": "Personal Care",
        "text": "Deodorants, Body Wash, Hand Wash, Grooming",
        "url": "/our-brands/personal-care/"
      },
      {
        "category": "cosmetics",
        "subcategories": [ "skin-care" ],
        "type": "own",
        "countries": [ "Czech", "Slovakia" ],
        "partner": "",
        "logo": "/media/ffudry10/indulona-logo.png?width=0\u0026height=150\u0026mode=crop\u0026quality=60",
        "title": "Personal Care",
        "text": "Skin Care",
        "url": "/our-brands/personal-care/"
      },
      {
        "category": "cosmetics",
        "subcategories": [ "personal-hygiene" ],
        "type": "distributed",
        "countries": [ "Romania", "Serbia" ],
        "partner": "johnson-johnson",
        "logo": "/media/femakgxn/carefree-logo.png?width=0\u0026height=150\u0026mode=crop\u0026quality=60",
        "title": "Personal Care",
        "text": "Personal Hygiene",
        "url": "/our-brands/personal-care/"
      },
      {
        "category": "cosmetics",
        "subcategories": [ "baby-care" ],
        "type": "distributed",
        "countries": [ "Romania", "Serbia" ],
        "partner": "johnson-johnson",
        "logo": "/media/301lbajs/johnson-s-logo.png?width=0\u0026height=150\u0026mode=crop\u0026quality=60",
        "title": "Personal Care",
        "text": "Baby Care",
        "url": "/our-brands/personal-care/"
      },
      {
        "category": "cosmetics",
        "subcategories": [ "oral-care" ],
        "type": "distributed",
        "countries": [ "Romania", "Serbia" ],
        "partner": "johnson-johnson",
        "logo": "/media/yk2ft4ss/listerine-logo.png?width=0\u0026height=150\u0026mode=crop\u0026quality=60",
        "title": "Personal Care",
        "text": "Oral Care",
        "url": "/our-brands/personal-care/"
      },
      {
        "category": "cosmetics",
        "subcategories": [ "skin-care", "body-wash", "hair-care" ],
        "type": "distributed",
        "countries": [ "Romania", "Serbia" ],
        "partner": "johnson-johnson",
        "logo": "/media/wzeldpl4/lpmlogo.png?width=0\u0026height=150\u0026mode=crop\u0026quality=60",
        "title": "Personal Care",
        "text": "Skin Care, Body Wash, Hair Care",
        "url": "/our-brands/personal-care/"
      },
      {
        "category": "cosmetics",
        "subcategories": [ "skin-care" ],
        "type": "distributed",
        "countries": [ "Romania", "Serbia" ],
        "partner": "johnson-johnson",
        "logo": "/media/fcddm1qu/neutrogena-black.png?width=0\u0026height=150\u0026mode=crop\u0026quality=60",
        "title": "Personal Care",
        "text": "Skin Care",
        "url": "/our-brands/personal-care/"
      },
      {
        "category": "cosmetics",
        "subcategories": [ "personal-hygiene" ],
        "type": "distributed",
        "countries": [ "Romania", "Serbia" ],
        "partner": "johnson-johnson",
        "logo": "/media/3urpsvxl/o-b-logo.png?width=0\u0026height=150\u0026mode=crop\u0026quality=60",
        "title": "Personal Care",
        "text": "Personal Hygiene",
        "url": "/our-brands/personal-care/"
      },
      {
        "category": "cosmetics",
        "subcategories": [ "sun-care" ],
        "type": "distributed",
        "countries": [ "Romania", "Serbia" ],
        "partner": "johnson-johnson",
        "logo": "/media/uejijuma/piz-buin-logo.png?width=0\u0026height=150\u0026mode=crop\u0026quality=60",
        "title": "Personal Care",
        "text": "Sun Care",
        "url": "/our-brands/personal-care/"
      },
      {
        "category": "cosmetics",
        "subcategories": [ "shaving-products" ],
        "type": "distributed",
        "countries": [ "Romania" ],
        "partner": "edgewell",
        "logo": "/media/zcgfcppk/ws-logo.png?width=0\u0026height=150\u0026mode=crop\u0026quality=60",
        "title": "Personal Care",
        "text": "Shaving Products",
        "url": "/our-brands/personal-care/"
      },
      {
        "category": "cosmetics",
        "subcategories": [ "skin-care", "body-wash" ],
        "type": "distributed",
        "countries": [ "Bulgaria" ],
        "partner": "sodalis-group",
        "logo": "/media/ifepxat5/leocrema-logo.png?width=0\u0026height=150\u0026mode=crop\u0026quality=60",
        "title": "Personal Care",
        "text": "Skin Care, Body Wash",
        "url": "/our-brands/personal-care/"
      },
      {
        "category": "cosmetics",
        "subcategories": [ "baby-care" ],
        "type": "distributed",
        "countries": [ "Bulgaria" ],
        "partner": "lavena",
        "logo": "/media/qjuku15o/bochko-logo.png?width=0\u0026height=150\u0026mode=crop\u0026quality=60",
        "title": "Personal Care",
        "text": "Baby Care",
        "url": "/our-brands/personal-care/"
      },
      {
        "category": "cosmetics",
        "subcategories": [ "skin-care" ],
        "type": "distributed",
        "countries": [ "Bulgaria" ],
        "partner": "lavena",
        "logo": "/media/4k3pyscq/my-rose-logo.png?width=0\u0026height=150\u0026mode=crop\u0026quality=60",
        "title": "Personal Care",
        "text": "Skin Care",
        "url": "/our-brands/personal-care/"
      },
      {
        "category": "cosmetics",
        "subcategories": [ "hair-care" ],
        "type": "distributed",
        "countries": [ "Bosnia", "North-Macedonia", "Serbia" ],
        "partner": "sodalis-group",
        "logo": "/media/c00jdmwl/gaia-logo.png?width=0\u0026height=150\u0026mode=crop\u0026quality=60",
        "title": "Personal Care",
        "text": "Hair Care",
        "url": "/our-brands/personal-care/"
      },
      {
        "category": "cosmetics",
        "subcategories": [ "hair-care" ],
        "type": "distributed",
        "countries": [ "Serbia" ],
        "partner": "sodalis-group",
        "logo": "/media/e5fhtv12/biopoint-logo.png?width=0\u0026height=150\u0026mode=crop\u0026quality=60",
        "title": "Personal Care",
        "text": "Hair Care",
        "url": "/our-brands/personal-care/"
      },
      {
        "category": "cosmetics",
        "subcategories": [ "Fragrances" ],
        "type": "distributed",
        "countries": [ "Serbia" ],
        "partner": "puig",
        "logo": "/media/2mrdiby2/benettonlogo.png?width=0\u0026height=150\u0026mode=crop\u0026quality=60",
        "title": "Personal Care",
        "text": "Fragrances",
        "url": "/our-brands/personal-care/"
      },
      {
        "category": "cosmetics",
        "subcategories": [ "Fragrances" ],
        "type": "distributed",
        "countries": [ "Czech", "Slovakia" ],
        "partner": "tailored-perfumes",
        "logo": "/media/nbnm2nie/pepejeans-logo.png?width=0\u0026height=150\u0026mode=crop\u0026quality=60",
        "title": "Personal Care",
        "text": "Fragrances",
        "url": "/our-brands/personal-care/"
      },
      {
        "category": "cosmetics",
        "subcategories": [ "skin-care" ],
        "type": "own",
        "countries": [ "Czech", "Slovakia" ],
        "partner": "",
        "logo": "/media/lgzbgsmz/peo-logo.png?width=0\u0026height=150\u0026mode=crop\u0026quality=60",
        "title": "Personal Care",
        "text": "Skin Care",
        "url": "/our-brands/personal-care/"
      },
      {
        "category": "cosmetics",
        "subcategories": [ "grooming" ],
        "type": "own",
        "countries": [ "Czech", "Slovakia" ],
        "partner": "",
        "logo": "/media/ylufikyw/diplomat-logo.png?width=0\u0026height=150\u0026mode=crop\u0026quality=60",
        "title": "Personal Care",
        "text": "Grooming",
        "url": "/our-brands/personal-care/"
      },
      {
        "category": "cosmetics",
        "subcategories": [ "hand-wash" ],
        "type": "distributed",
        "countries": [ "Czech" ],
        "partner": "evyap",
        "logo": "/media/m32cholf/fax-logo.png?width=0\u0026height=150\u0026mode=crop\u0026quality=60",
        "title": "Personal Care",
        "text": "Hand Wash",
        "url": "/our-brands/personal-care/"
      },
      {
        "category": "cosmetics",
        "subcategories": [ "hair-styling" ],
        "type": "distributed",
        "countries": [ "Greece" ],
        "partner": "coty",
        "logo": "/media/rsjhb3s1/new-wave-logo.png?width=0\u0026height=150\u0026mode=crop\u0026quality=60",
        "title": "Personal Care",
        "text": "Hair Styling",
        "url": "/our-brands/personal-care/"
      },
      {
        "category": "cosmetics",
        "subcategories": [ "hair-styling" ],
        "type": "distributed",
        "countries": [ "Greece" ],
        "partner": "coty",
        "logo": "/media/fiti3ije/wellaflex-logo.png?width=0\u0026height=150\u0026mode=crop\u0026quality=60",
        "title": "Personal Care",
        "text": "Hair Styling",
        "url": "/our-brands/personal-care/"
      },
      {
        "category": "cosmetics",
        "subcategories": [ "hair-styling" ],
        "type": "distributed",
        "countries": [ "Greece" ],
        "partner": "coty",
        "logo": "/media/sytcjxoj/welladeluxe-logo.png?width=0\u0026height=150\u0026mode=crop\u0026quality=60",
        "title": "Personal Care",
        "text": "Hair Styling",
        "url": "/our-brands/personal-care/"
      },
      {
        "category": "cosmetics",
        "subcategories": [ "oral-care" ],
        "type": "distributed",
        "countries": [ "Bulgaria" ],
        "partner": "church-dwight",
        "logo": "/media/bnlh5yxk/arm-hammer.png?width=0\u0026height=150\u0026mode=crop\u0026quality=60",
        "title": "Personal Care",
        "text": "Oral Care",
        "url": "/our-brands/personal-care/"
      },
      {
        "category": "cosmetics",
        "subcategories": [ "hand-wash" ],
        "type": "distributed",
        "countries": [ "Poland" ],
        "partner": "pz-cussons",
        "logo": "/media/f5ugeam5/carex-logo.png?width=0\u0026height=150\u0026mode=crop\u0026quality=60",
        "title": "Personal Care",
        "text": "Hand Wash",
        "url": "/our-brands/personal-care/"
      },
      {
        "category": "cosmetics",
        "subcategories": [ "body-wash" ],
        "type": "distributed",
        "countries": [ "Poland" ],
        "partner": "pz-cussons",
        "logo": "/media/fwvba2pd/original-source-logo.png?width=0\u0026height=150\u0026mode=crop\u0026quality=60",
        "title": "Personal Care",
        "text": "Body Wash",
        "url": "/our-brands/personal-care/"
      },
      {
        "category": "cosmetics",
        "subcategories": [ "Fragrances" ],
        "type": "distributed",
        "countries": [ "Hungary", "Poland" ],
        "partner": "parlux",
        "logo": "/media/ac1hyy0o/pierrecardin-logo.png?width=0\u0026height=150\u0026mode=crop\u0026quality=60",
        "title": "Personal Care",
        "text": "Fragrances",
        "url": "/our-brands/personal-care/"
      },
      {
        "category": "cosmetics",
        "subcategories": [ "Fragrances" ],
        "type": "distributed",
        "countries": [ "Poland" ],
        "partner": "parlux",
        "logo": "/media/cu4dq1bs/paris-logo-black.png?width=0\u0026height=150\u0026mode=crop\u0026quality=60",
        "title": "Personal Care",
        "text": "Fragrances",
        "url": "/our-brands/personal-care/"
      },
      {
        "category": "cosmetics",
        "subcategories": [ "sun-care" ],
        "type": "distributed",
        "countries": [ "Poland" ],
        "partner": "marque-of-brands",
        "logo": "/media/ru2khyui/b-tan-logo.png?width=0\u0026height=150\u0026mode=crop\u0026quality=60",
        "title": "Personal Care",
        "text": "Sun Care",
        "url": "/our-brands/personal-care/"
      },
      {
        "category": "cosmetics",
        "subcategories": [ "skin-care", "body-wash", "sun-care" ],
        "type": "own",
        "countries": [ "Romania" ],
        "partner": "",
        "logo": "/media/bl5cwbwx/elmiplant-logo.png?width=0\u0026height=150\u0026mode=crop\u0026quality=60",
        "title": "Personal Care",
        "text": "Skin Care, Body Wash, Sun Care",
        "url": "/our-brands/personal-care/"
      },
      {
        "category": "cosmetics",
        "subcategories": [ "Fragrances" ],
        "type": "distributed",
        "countries": [ "Bulgaria", "Greece", "North-Macedonia", "Romania", "Serbia" ],
        "partner": "puig",
        "logo": "/media/4e3daqne/ab-logo.png?width=0\u0026height=150\u0026mode=crop\u0026quality=60",
        "title": "Personal Care",
        "text": "Fragrances",
        "url": "/our-brands/personal-care/"
      },
      {
        "category": "cosmetics",
        "subcategories": [ "hair-care" ],
        "type": "distributed",
        "countries": [ "Bosnia", "Bulgaria", "Greece", "Hungary", "North-Macedonia", "Serbia" ],
        "partner": "church-dwight",
        "logo": "/media/nbzb3abv/batiste-logo.png?width=0\u0026height=150\u0026mode=crop\u0026quality=60",
        "title": "Personal Care",
        "text": "Hair Care",
        "url": "/our-brands/personal-care/"
      },
      {
        "category": "cosmetics",
        "subcategories": [ "Fragrances", "body-wash", "hand-wash", "skin-care", "deodorants" ],
        "type": "distributed",
        "countries": [ "Bosnia", "Bulgaria", "Czech", "Greece", "Hungary", "North-Macedonia", "Romania", "Serbia", "Slovakia" ],
        "partner": "sodalis-group",
        "logo": "/media/2spis5ay/tdo-logo.png?width=0\u0026height=150\u0026mode=crop\u0026quality=60",
        "title": "Personal Care",
        "text": "Fragrances, Body Wash, Hand Wash, Skin Care, Deodorants",
        "url": "/our-brands/personal-care/"
      },
      {
        "category": "cosmetics",
        "subcategories": [ "body-wash", "hand-wash" ],
        "type": "distributed",
        "countries": [ "Bosnia", "Czech", "Greece", "Romania", "Serbia", "Slovakia" ],
        "partner": "sodalis-group",
        "logo": "/media/el4pav1b/vidal-logo-περιγραμμα.png?width=0\u0026height=150\u0026mode=crop\u0026quality=60",
        "title": "Personal Care",
        "text": "Body Wash, Hand Wash",
        "url": "/our-brands/personal-care/"
      },
      {
        "category": "cosmetics",
        "subcategories": [ "hair-care" ],
        "type": "distributed",
        "countries": [ "Bosnia", "Bulgaria", "Greece", "North-Macedonia", "Poland", "Romania", "Serbia" ],
        "partner": "sodalis-group",
        "logo": "/media/cmtpyogu/w-g-logo-finalgreen.png?width=0\u0026height=150\u0026mode=crop\u0026quality=60",
        "title": "Personal Care",
        "text": "Hair Care",
        "url": "/our-brands/personal-care/"
      },
      {
        "category": "cosmetics",
        "subcategories": [ "Fragrances", "deodorants", "body-wash" ],
        "type": "distributed",
        "countries": [ "Bosnia", "Bulgaria", "Czech", "Greece", "Hungary", "North-Macedonia", "Poland", "Romania", "Serbia", "Slovakia" ],
        "partner": "sodalis-group",
        "logo": "/media/xrabe3vo/denim-logo.png?width=0\u0026height=150\u0026mode=crop\u0026quality=60",
        "title": "Personal Care",
        "text": "Fragrances, Deodorants, Body Wash",
        "url": "/our-brands/personal-care/"
      },
      {
        "category": "cosmetics",
        "subcategories": [ "grooming" ],
        "type": "distributed",
        "countries": [ "Greece" ],
        "partner": "church-dwight",
        "logo": "/media/3tcegez4/ναιr-logo.png?width=0\u0026height=150\u0026mode=crop\u0026quality=60",
        "title": "Personal Care",
        "text": "Grooming",
        "url": "/our-brands/personal-care/"
      },
      {
        "category": "cosmetics",
        "subcategories": [ "hair-colorant" ],
        "type": "distributed",
        "countries": [ "Greece" ],
        "partner": "coty",
        "logo": "/media/mblag33b/koleston-logo.png?width=0\u0026height=150\u0026mode=crop\u0026quality=60",
        "title": "Personal Care",
        "text": "Hair Colorant",
        "url": "/our-brands/personal-care/"
      }
    ]
  },
  {
    "id": 2,
    "category": "luxury",
    "text": "Luxury",
    "subcategories": [ "bathroom-cleaners", "cleaning-tools", "dishwashing", "drainer-care", "food-packaging", "garbage-bags", "insect-control", "septic-tank-activator", "shoe-care" ],
    "products": [
      {
        "category": "luxury",
        "subcategories": [ "food-packaging", "garbage-bags", "cleaning-tools" ],
        "type": "own",
        "countries": [ "Greece" ],
        "partner": "",
        "logo": "/media/5ybi3piz/rsz_logo_sanitas.png?width=0\u0026height=150\u0026mode=crop\u0026quality=60",
        "title": "Home Care",
        "text": "Food Packaging, Garbage Bags, Cleaning Tools",
        "url": "/our-brands/home-care/"
      },
      {
        "category": "luxury",
        "subcategories": [ "dishwashing" ],
        "type": "own",
        "countries": [ "Greece" ],
        "partner": "",
        "logo": "/media/y1lj3upj/ava-removebg-preview.png?width=0\u0026height=150\u0026mode=crop\u0026quality=60",
        "title": "Home Care",
        "text": "Dishwashing",
        "url": "/our-brands/home-care/"
      },
      {
        "category": "luxury",
        "subcategories": [ "insect-control" ],
        "type": "own",
        "countries": [ "Greece", "Poland" ],
        "partner": "",
        "logo": "/media/myshowco/rsz_teza_logotype.png?width=0\u0026height=150\u0026mode=crop\u0026quality=60",
        "title": "Home Care",
        "text": "Insect Control",
        "url": "/our-brands/home-care/"
      },
      {
        "category": "luxury",
        "subcategories": [ "insect-control" ],
        "type": "own",
        "countries": [ "Greece" ],
        "partner": "",
        "logo": "/media/wnrncear/rsz_pyrox_logo_cmyk-03.png?width=0\u0026height=150\u0026mode=crop\u0026quality=60",
        "title": "Home Care",
        "text": "Insect Control",
        "url": "/our-brands/home-care/"
      },
      {
        "category": "luxury",
        "subcategories": [ "bathroom-cleaners" ],
        "type": "own",
        "countries": [ "Greece" ],
        "partner": "",
        "logo": "/media/ts0llj1j/logo_afroso_new.png?width=0\u0026height=150\u0026mode=crop\u0026quality=60",
        "title": "Home Care",
        "text": "Bathroom Cleaners",
        "url": "/our-brands/home-care/"
      },
      {
        "category": "luxury",
        "subcategories": [ "drainer-care" ],
        "type": "own",
        "countries": [ "Bosnia", "Bulgaria", "Czech", "Greece", "Hungary", "North-Macedonia", "Romania", "Serbia", "Slovakia" ],
        "partner": "",
        "logo": "/media/3qpatdiq/rsz_logo_tuboflo.png?width=0\u0026height=150\u0026mode=crop\u0026quality=60",
        "title": "Home Care",
        "text": "Drainer Care",
        "url": "/our-brands/home-care/"
      },
      {
        "category": "luxury",
        "subcategories": [ "shoe-care" ],
        "type": "own",
        "countries": [ "Greece" ],
        "partner": "",
        "logo": "/media/h43d3fnv/rsz_camel.png?width=0\u0026height=150\u0026mode=crop\u0026quality=60",
        "title": "Home Care",
        "text": "Shoe Care",
        "url": "/our-brands/home-care/"
      },
      {
        "category": "luxury",
        "subcategories": [ "dishwashing" ],
        "type": "distributed",
        "countries": [ "Poland" ],
        "partner": "pz-cussons",
        "logo": "/media/uz3duehr/morning_fresh_logo_550.png?width=0\u0026height=150\u0026mode=crop\u0026quality=60",
        "title": "Home Care",
        "text": "Dishwashing",
        "url": "/our-brands/home-care/"
      },
      {
        "category": "luxury",
        "subcategories": [ "septic-tank-activator" ],
        "type": "distributed",
        "countries": [ "Poland" ],
        "partner": "henkel",
        "logo": "/media/hpbcnfuj/rsz_septifos_logo.png?width=0\u0026height=150\u0026mode=crop\u0026quality=60",
        "title": "Home Care",
        "text": "Septic Tank Activator",
        "url": "/our-brands/home-care/"
      },
      {
        "category": "luxury",
        "subcategories": [ "food-packaging", "garbage-bags", "cleaning-tools" ],
        "type": "own",
        "countries": [ "Portugal" ],
        "partner": "",
        "logo": "/media/gawmaypl/jan_logo_550.png?width=0\u0026height=150\u0026mode=crop\u0026quality=60",
        "title": "Home Care",
        "text": "Food Packaging, Garbage Bags, Cleaning Tools",
        "url": "/our-brands/home-care/"
      },
      {
        "category": "luxury",
        "subcategories": [ "food-packaging", "garbage-bags", "cleaning-tools" ],
        "type": "own",
        "countries": [ "Poland" ],
        "partner": "",
        "logo": "/media/ewdksvam/rsz_grosik_logo_nowe-removebg-preview.png?width=0\u0026height=150\u0026mode=crop\u0026quality=60",
        "title": "Home Care",
        "text": "Food Packaging, Garbage Bags, Cleaning Tools",
        "url": "/our-brands/home-care/"
      },
      {
        "category": "luxury",
        "subcategories": [ "food-packaging", "garbage-bags", "cleaning-tools" ],
        "type": "own",
        "countries": [ "Russia", "Ukraine" ],
        "partner": "",
        "logo": "/media/cpmnwmeo/rsz_mg_logo_no_shadow-removebg-preview.png?width=0\u0026height=150\u0026mode=crop\u0026quality=60",
        "title": "Home Care",
        "text": "Food Packaging, Garbage Bags, Cleaning Tools",
        "url": "/our-brands/home-care/"
      },
      {
        "category": "luxury",
        "subcategories": [ "garbage-bags", "cleaning-tools" ],
        "type": "own",
        "countries": [ "Russia", "Ukraine" ],
        "partner": "",
        "logo": "/media/po5grstq/rsz_domi_logo-removebg-preview.png?width=0\u0026height=150\u0026mode=crop\u0026quality=60",
        "title": "Home Care",
        "text": "Garbage Bags, Cleaning Tools",
        "url": "/our-brands/home-care/"
      },
      {
        "category": "luxury",
        "subcategories": [ "food-packaging", "garbage-bags", "cleaning-tools" ],
        "type": "own",
        "countries": [ "Russia", "Ukraine" ],
        "partner": "",
        "logo": "/media/u3antqz4/novax_logo_550.png?width=0\u0026height=150\u0026mode=crop\u0026quality=60",
        "title": "Home Care",
        "text": "Food Packaging, Garbage Bags, Cleaning Tools",
        "url": "/our-brands/home-care/"
      },
      {
        "category": "luxury",
        "subcategories": [ "food-packaging", "garbage-bags", "cleaning-tools" ],
        "type": "own",
        "countries": [ "Bosnia", "Bulgaria", "Czech", "Greece", "North-Macedonia", "Portugal", "Romania", "Serbia", "Slovakia" ],
        "partner": "",
        "logo": "/media/k1adfag2/fino_logo_550.png?width=0\u0026height=150\u0026mode=crop\u0026quality=60",
        "title": "Home Care",
        "text": "Food Packaging, Garbage Bags, Cleaning Tools",
        "url": "/our-brands/home-care/"
      },
      {
        "category": "luxury",
        "subcategories": [ "food-packaging", "garbage-bags", "cleaning-tools" ],
        "type": "own",
        "countries": [ "Bosnia", "Bulgaria", "Czech", "Hungary", "North-Macedonia", "Romania", "Serbia", "Slovakia" ],
        "partner": "",
        "logo": "/media/vkonsgxk/rsz_top_star_logo__white_bg_-removebg-preview.png?width=0\u0026height=150\u0026mode=crop\u0026quality=60",
        "title": "Home Care",
        "text": "Food Packaging, Garbage Bags, Cleaning Tools",
        "url": "/our-brands/home-care/"
      },
      {
        "category": "luxury",
        "subcategories": [ "food-packaging", "garbage-bags", "cleaning-tools" ],
        "type": "own",
        "countries": [ "Hungary" ],
        "partner": "",
        "logo": "/media/gqxnq4sg/rsz_hewa_logo.png?width=0\u0026height=150\u0026mode=crop\u0026quality=60",
        "title": "Home Care",
        "text": "Food Packaging, Garbage Bags, Cleaning Tools",
        "url": "/our-brands/home-care/"
      },
      {
        "category": "luxury",
        "subcategories": [ "garbage-bags" ],
        "type": "own",
        "countries": [ "Poland-Polipak" ],
        "partner": "",
        "logo": "/media/xjtecwuk/logo_polipak-removebg-preview.png?width=0\u0026height=150\u0026mode=crop\u0026quality=60",
        "title": "Home Care",
        "text": "Garbage Bags",
        "url": "/our-brands/home-care/"
      }
    ]
  },
  {
    "id": 3,
    "category": "home",
    "text": "Home",
    "subcategories": [ "food-supplements", "health-self-care", "skin-care", "sun-care" ],
    "products": [
      {
        "category": "home",
        "subcategories": [ "skin-care" ],
        "type": "distributed",
        "countries": [ "Greece" ],
        "partner": "union-swiss",
        "logo": "/media/gibh23az/bio-oil-transparent-logo.png?width=0\u0026height=150\u0026mode=crop\u0026quality=60",
        "title": "Health Care",
        "text": "Skin Care",
        "url": "/our-brands/health-care/"
      },
      {
        "category": "home",
        "subcategories": [ "food-supplements" ],
        "type": "distributed",
        "countries": [ "Greece" ],
        "partner": "g-r-lane-health-products",
        "logo": "/media/jtad52y5/rsz_logo_lanes_1-removebg-preview.png?width=0\u0026height=150\u0026mode=crop\u0026quality=60",
        "title": "Health Care",
        "text": "Food Supplements",
        "url": "/our-brands/health-care/"
      },
      {
        "category": "home",
        "subcategories": [ "sun-care" ],
        "type": "own",
        "countries": [ "Greece" ],
        "partner": "",
        "logo": "/media/5eqhxnr5/rsz_solene_logo_1.png?width=0\u0026height=150\u0026mode=crop\u0026quality=60",
        "title": "Health Care",
        "text": "Sun Care",
        "url": "/our-brands/health-care/"
      },
      {
        "category": "home",
        "subcategories": [ "food-supplements" ],
        "type": "distributed",
        "countries": [ "Greece" ],
        "partner": "ortis",
        "logo": "/media/230lxsmb/output-onlinepngtools.png?width=0\u0026height=150\u0026mode=crop\u0026quality=60",
        "title": "Health Care",
        "text": "Food Supplements",
        "url": "/our-brands/health-care/"
      },
      {
        "category": "home",
        "subcategories": [ "health-self-care" ],
        "type": "distributed",
        "countries": [ "Romania" ],
        "partner": "",
        "logo": "/media/b1ennwqw/pic-logo.png?width=0\u0026height=150\u0026mode=crop\u0026quality=60",
        "title": "Health Care",
        "text": "Health Self Care",
        "url": "/our-brands/health-care/"
      },
      {
        "category": "home",
        "subcategories": [ "skin-care" ],
        "type": "own",
        "countries": [ "Greece" ],
        "partner": "",
        "logo": "/media/yzepd0zb/logo-filovit-550x550pxls.png?width=0\u0026height=150\u0026mode=crop\u0026quality=60",
        "title": "Health Care",
        "text": "Skin Care",
        "url": "/our-brands/health-care/"
      },
      {
        "category": "home",
        "subcategories": [ "health-self-care" ],
        "type": "distributed",
        "countries": [ "Romania" ],
        "partner": "laboratoire-hra-pharma",
        "logo": "/media/kn5bzxnf/rsz_compeed_keeps_you_on_track_lock-up_teal_cmyk_1-removebg-preview.png?width=0\u0026height=150\u0026mode=crop\u0026quality=60",
        "title": "Health Care",
        "text": "Health Self Care",
        "url": "/our-brands/health-care/"
      }
    ]
  },
  {
    "id": 4,
    "category": "professional",
    "text": "Professional",
    "subcategories": [ "Fragrances", "home-fragrances", "Make-Up", "Treatment" ],
    "products": [
      {
        "category": "professional",
        "subcategories": [ "Fragrances" ],
        "type": "distributed",
        "countries": [ "Greece" ],
        "partner": "coty",
        "logo": "/media/1uahnv1w/balenciagalogo-1-550_transparent.png?width=0\u0026height=150\u0026mode=crop\u0026quality=60",
        "title": "Luxury Cosmetics",
        "text": "Fragrances",
        "url": "/our-brands/luxury-cosmetics/"
      },
      {
        "category": "professional",
        "subcategories": [ "Fragrances" ],
        "type": "distributed",
        "countries": [ "Greece" ],
        "partner": "coty",
        "logo": "/media/dh4pseja/logo.png?width=0\u0026height=150\u0026mode=crop\u0026quality=60",
        "title": "Luxury Cosmetics",
        "text": "Fragrances",
        "url": "/our-brands/luxury-cosmetics/"
      },
      {
        "category": "professional",
        "subcategories": [ "Fragrances" ],
        "type": "distributed",
        "countries": [ "Greece" ],
        "partner": "coty",
        "logo": "/media/hrkjyhua/burberrylogo.png?width=0\u0026height=150\u0026mode=crop\u0026quality=60",
        "title": "Luxury Cosmetics",
        "text": "Fragrances",
        "url": "/our-brands/luxury-cosmetics/"
      },
      {
        "category": "professional",
        "subcategories": [ "Fragrances" ],
        "type": "distributed",
        "countries": [ "Greece" ],
        "partner": "coty",
        "logo": "/media/4ion3bpf/calvin_kleinlogo.png?width=0\u0026height=150\u0026mode=crop\u0026quality=60",
        "title": "Luxury Cosmetics",
        "text": "Fragrances",
        "url": "/our-brands/luxury-cosmetics/"
      },
      {
        "category": "professional",
        "subcategories": [ "Fragrances" ],
        "type": "distributed",
        "countries": [ "Bulgaria", "Greece", "Romania" ],
        "partner": "puig",
        "logo": "/media/giqg4g4c/ch_logo.png?width=0\u0026height=150\u0026mode=crop\u0026quality=60",
        "title": "Luxury Cosmetics",
        "text": "Fragrances",
        "url": "/our-brands/luxury-cosmetics/"
      },
      {
        "category": "professional",
        "subcategories": [ "Fragrances" ],
        "type": "distributed",
        "countries": [ "Greece" ],
        "partner": "cartier",
        "logo": "/media/eezbywdc/logo-cartier.png?width=0\u0026height=150\u0026mode=crop\u0026quality=60",
        "title": "Luxury Cosmetics",
        "text": "Fragrances",
        "url": "/our-brands/luxury-cosmetics/"
      },
      {
        "category": "professional",
        "subcategories": [ "Fragrances" ],
        "type": "distributed",
        "countries": [ "Greece" ],
        "partner": "coty",
        "logo": "/media/l0vgl5no/chloe_logo.png?width=0\u0026height=150\u0026mode=crop\u0026quality=60",
        "title": "Luxury Cosmetics",
        "text": "Fragrances",
        "url": "/our-brands/luxury-cosmetics/"
      },
      {
        "category": "professional",
        "subcategories": [ "Fragrances" ],
        "type": "distributed",
        "countries": [ "Greece", "Romania" ],
        "partner": "chopard",
        "logo": "/media/sjlp0h1w/chopard_logo-removebg-preview.png?width=0\u0026height=150\u0026mode=crop\u0026quality=60",
        "title": "Luxury Cosmetics",
        "text": "Fragrances",
        "url": "/our-brands/luxury-cosmetics/"
      },
      {
        "category": "professional",
        "subcategories": [ "Fragrances" ],
        "type": "distributed",
        "countries": [ "Greece" ],
        "partner": "coty",
        "logo": "/media/3oedcmkt/logo_davidoff_new.png?width=0\u0026height=150\u0026mode=crop\u0026quality=60",
        "title": "Luxury Cosmetics",
        "text": "Fragrances",
        "url": "/our-brands/luxury-cosmetics/"
      },
      {
        "category": "professional",
        "subcategories": [ "Fragrances" ],
        "type": "distributed",
        "countries": [ "Greece" ],
        "partner": "coty",
        "logo": "/media/3hmchoxo/escada-logo.png?width=0\u0026height=150\u0026mode=crop\u0026quality=60",
        "title": "Luxury Cosmetics",
        "text": "Fragrances",
        "url": "/our-brands/luxury-cosmetics/"
      },
      {
        "category": "professional",
        "subcategories": [ "Fragrances" ],
        "type": "distributed",
        "countries": [ "Greece" ],
        "partner": "angelini-group",
        "logo": "/media/h1tnhk4p/ferre-logo.png?width=0\u0026height=150\u0026mode=crop\u0026quality=60",
        "title": "Luxury Cosmetics",
        "text": "Fragrances",
        "url": "/our-brands/luxury-cosmetics/"
      },
      {
        "category": "professional",
        "subcategories": [ "Treatment" ],
        "type": "distributed",
        "countries": [ "Greece" ],
        "partner": "grown-alchemist",
        "logo": "/media/0ctik13y/ga-logo.png?width=0\u0026height=150\u0026mode=crop\u0026quality=60",
        "title": "Luxury Cosmetics",
        "text": "Treatment",
        "url": "/our-brands/luxury-cosmetics/"
      },
      {
        "category": "professional",
        "subcategories": [ "Fragrances" ],
        "type": "distributed",
        "countries": [ "Greece" ],
        "partner": "coty",
        "logo": "/media/bcsbuhnf/gucci-logo.png?width=0\u0026height=150\u0026mode=crop\u0026quality=60",
        "title": "Luxury Cosmetics",
        "text": "Fragrances",
        "url": "/our-brands/luxury-cosmetics/"
      },
      {
        "category": "professional",
        "subcategories": [ "Fragrances" ],
        "type": "distributed",
        "countries": [ "Greece" ],
        "partner": "coty",
        "logo": "/media/qdehsoxz/hugo-boss-logo.png?width=0\u0026height=150\u0026mode=crop\u0026quality=60",
        "title": "Luxury Cosmetics",
        "text": "Fragrances",
        "url": "/our-brands/luxury-cosmetics/"
      },
      {
        "category": "professional",
        "subcategories": [ "Fragrances" ],
        "type": "distributed",
        "countries": [ "Bulgaria", "Greece", "Romania" ],
        "partner": "puig",
        "logo": "/media/r44dm2jv/jpg-logo.png?width=0\u0026height=150\u0026mode=crop\u0026quality=60",
        "title": "Luxury Cosmetics",
        "text": "Fragrances",
        "url": "/our-brands/luxury-cosmetics/"
      },
      {
        "category": "professional",
        "subcategories": [ "Fragrances" ],
        "type": "distributed",
        "countries": [ "Greece" ],
        "partner": "coty",
        "logo": "/media/0b5l32yn/joop-logo.png?width=0\u0026height=150\u0026mode=crop\u0026quality=60",
        "title": "Luxury Cosmetics",
        "text": "Fragrances",
        "url": "/our-brands/luxury-cosmetics/"
      },
      {
        "category": "professional",
        "subcategories": [ "Treatment" ],
        "type": "distributed",
        "countries": [ "Bulgaria", "Greece", "Poland", "Romania" ],
        "partner": "la-prairie-group",
        "logo": "/media/ynvfosnz/la-prairie-logo.png?width=0\u0026height=150\u0026mode=crop\u0026quality=60",
        "title": "Luxury Cosmetics",
        "text": "Treatment",
        "url": "/our-brands/luxury-cosmetics/"
      },
      {
        "category": "professional",
        "subcategories": [ "Fragrances" ],
        "type": "distributed",
        "countries": [ "Greece" ],
        "partner": "lalique",
        "logo": "/media/bq2eqmja/lalique-logo.png?width=0\u0026height=150\u0026mode=crop\u0026quality=60",
        "title": "Luxury Cosmetics",
        "text": "Fragrances",
        "url": "/our-brands/luxury-cosmetics/"
      },
      {
        "category": "professional",
        "subcategories": [ "Fragrances" ],
        "type": "distributed",
        "countries": [ "Greece" ],
        "partner": "coty",
        "logo": "/media/j4hior3x/marc-jabocs-logo.png?width=0\u0026height=150\u0026mode=crop\u0026quality=60",
        "title": "Luxury Cosmetics",
        "text": "Fragrances",
        "url": "/our-brands/luxury-cosmetics/"
      },
      {
        "category": "professional",
        "subcategories": [ "Fragrances" ],
        "type": "distributed",
        "countries": [ "Bulgaria", "Greece" ],
        "partner": "puig",
        "logo": "/media/5isjl1ix/nina-ricci-logo.png?width=0\u0026height=150\u0026mode=crop\u0026quality=60",
        "title": "Luxury Cosmetics",
        "text": "Fragrances",
        "url": "/our-brands/luxury-cosmetics/"
      },
      {
        "category": "professional",
        "subcategories": [ "Fragrances" ],
        "type": "distributed",
        "countries": [ "Bulgaria", "Greece", "Romania" ],
        "partner": "puig",
        "logo": "/media/nhdl54cq/paco-rabanne-logo.png?width=0\u0026height=150\u0026mode=crop\u0026quality=60",
        "title": "Luxury Cosmetics",
        "text": "Fragrances",
        "url": "/our-brands/luxury-cosmetics/"
      },
      {
        "category": "professional",
        "subcategories": [ "Fragrances" ],
        "type": "distributed",
        "countries": [ "Greece" ],
        "partner": "puig",
        "logo": "/media/e55fpeqa/prada-logo.png?width=0\u0026height=150\u0026mode=crop\u0026quality=60",
        "title": "Luxury Cosmetics",
        "text": "Fragrances",
        "url": "/our-brands/luxury-cosmetics/"
      },
      {
        "category": "professional",
        "subcategories": [ "Fragrances" ],
        "type": "distributed",
        "countries": [ "Greece" ],
        "partner": "coty",
        "logo": "/media/cenggyms/cavalli-logo.png?width=0\u0026height=150\u0026mode=crop\u0026quality=60",
        "title": "Luxury Cosmetics",
        "text": "Fragrances",
        "url": "/our-brands/luxury-cosmetics/"
      },
      {
        "category": "professional",
        "subcategories": [ "Fragrances" ],
        "type": "distributed",
        "countries": [ "Bulgaria", "Greece" ],
        "partner": "salvatore-ferragamo",
        "logo": "/media/cbvnzpmz/ferragamo_logo_new.png?width=0\u0026height=150\u0026mode=crop\u0026quality=60",
        "title": "Luxury Cosmetics",
        "text": "Fragrances",
        "url": "/our-brands/luxury-cosmetics/"
      },
      {
        "category": "professional",
        "subcategories": [ "Fragrances" ],
        "type": "distributed",
        "countries": [ "Greece" ],
        "partner": "coty",
        "logo": "/media/aqajfztf/tiffany-logo.png?width=0\u0026height=150\u0026mode=crop\u0026quality=60",
        "title": "Luxury Cosmetics",
        "text": "Fragrances",
        "url": "/our-brands/luxury-cosmetics/"
      },
      {
        "category": "professional",
        "subcategories": [ "Fragrances" ],
        "type": "distributed",
        "countries": [ "Bulgaria", "Greece" ],
        "partner": "angelini-group",
        "logo": "/media/hquccooa/τrussardi-logo.png?width=0\u0026height=150\u0026mode=crop\u0026quality=60",
        "title": "Luxury Cosmetics",
        "text": "Fragrances",
        "url": "/our-brands/luxury-cosmetics/"
      },
      {
        "category": "professional",
        "subcategories": [ "Treatment" ],
        "type": "distributed",
        "countries": [ "Greece" ],
        "partner": "coty",
        "logo": "/media/aj3pramw/lancaster-logo.png?width=0\u0026height=150\u0026mode=crop\u0026quality=60",
        "title": "Luxury Cosmetics",
        "text": "Treatment",
        "url": "/our-brands/luxury-cosmetics/"
      },
      {
        "category": "professional",
        "subcategories": [ "Make-Up" ],
        "type": "distributed",
        "countries": [ "Greece" ],
        "partner": "coty",
        "logo": "/media/vwzp2afe/logo-bourjois-final.png?width=0\u0026height=150\u0026mode=crop\u0026quality=60",
        "title": "Luxury Cosmetics",
        "text": "Make Up",
        "url": "/our-brands/luxury-cosmetics/"
      },
      {
        "category": "professional",
        "subcategories": [ "Make-Up" ],
        "type": "distributed",
        "countries": [ "Greece" ],
        "partner": "coty",
        "logo": "/media/c01brxxn/maxfactor-final-logo.png?width=0\u0026height=150\u0026mode=crop\u0026quality=60",
        "title": "Luxury Cosmetics",
        "text": "Make Up",
        "url": "/our-brands/luxury-cosmetics/"
      },
      {
        "category": "professional",
        "subcategories": [ "Make-Up" ],
        "type": "distributed",
        "countries": [ "Greece" ],
        "partner": "pupa-milano",
        "logo": "/media/e24lxbbg/pupa-logo.png?width=0\u0026height=150\u0026mode=crop\u0026quality=60",
        "title": "Luxury Cosmetics",
        "text": "Make Up",
        "url": "/our-brands/luxury-cosmetics/"
      },
      {
        "category": "professional",
        "subcategories": [ "Make-Up" ],
        "type": "distributed",
        "countries": [ "Greece" ],
        "partner": "coty",
        "logo": "/media/fgmfaeu5/rimmel-logo.png?width=0\u0026height=150\u0026mode=crop\u0026quality=60",
        "title": "Luxury Cosmetics",
        "text": "Make Up",
        "url": "/our-brands/luxury-cosmetics/"
      },
      {
        "category": "professional",
        "subcategories": [ "Fragrances" ],
        "type": "distributed",
        "countries": [ "Greece", "Romania" ],
        "partner": "philipp-plein-parfums-sa",
        "logo": "/media/2lleq2jh/philipp-plein-logo.png?width=0\u0026height=150\u0026mode=crop\u0026quality=60",
        "title": "Luxury Cosmetics",
        "text": "Fragrances",
        "url": "/our-brands/luxury-cosmetics/"
      },
      {
        "category": "professional",
        "subcategories": [ "home-fragrances" ],
        "type": "distributed",
        "countries": [ "Bulgaria" ],
        "partner": "dr-vranjes-firenze",
        "logo": "/media/hi3ij1j4/drvranjes_logo.png?width=0\u0026height=150\u0026mode=crop\u0026quality=60",
        "title": "Luxury Cosmetics",
        "text": "Home Fragrances",
        "url": "/our-brands/luxury-cosmetics/"
      }
    ]
  },
  {
    "id": 5,
    "category": "health",
    "text": "Health",
    "subcategories": [ "cleaning-tools", "detergents", "food-packaging", "garbage-bags", "packaging" ],
    "products": [
      {
        "category": "health",
        "subcategories": [ "food-packaging", "garbage-bags", "cleaning-tools", "detergents" ],
        "type": "own",
        "countries": [ "Greece" ],
        "partner": "",
        "logo": "/media/a40djrjk/sanitas-professional-logo.png?width=0\u0026height=150\u0026mode=crop\u0026quality=60",
        "title": "Professional Products",
        "text": "Food Packaging, Garbage Bags, Cleaning Tools, Detergents",
        "url": "/our-brands/professional-products/"
      },
      {
        "category": "health",
        "subcategories": [ "food-packaging" ],
        "type": "own",
        "countries": [ "Poland" ],
        "partner": "",
        "logo": "/media/pdrlfqda/professional.png?width=0\u0026height=150\u0026mode=crop\u0026quality=60",
        "title": "Professional Products",
        "text": "Food Packaging",
        "url": "/our-brands/professional-products/"
      },
      {
        "category": "health",
        "subcategories": [ "packaging" ],
        "type": "own",
        "countries": [ "Poland-Polipak" ],
        "partner": "",
        "logo": "/media/sn4ek12a/logo_polipak-removebg-preview.png?width=0\u0026height=150\u0026mode=crop\u0026quality=60",
        "title": "Professional Products",
        "text": "Packaging",
        "url": "/our-brands/professional-products/"
      }
    ]
  }
]